rillio/__init__.py
rillio-0.0.1.dist-info/METADATA
rillio-0.0.1.dist-info/WHEEL
rillio-0.0.1.dist-info/RECORD
