Metadata-Version: 2.4
Name: rillio
Version: 0.0.1
Summary: Pluggable, feature-aware database façade (name reservation)
Author: Suhail
Classifier: License :: OSI Approved :: MIT License
Classifier: Programming Language :: Python :: 3
Requires-Python: >=3.10
